fancytitle
