Metadata-Version: 2.1
Name: fancy-title
Version: 0.1.3
Summary: Evaluation metrics for your fancy title. The higher the better.
Home-page: https://github.com/cui-shaobo/fancy-title
Author: Shaobo Cui
Author-email: shaobo.cui@epfl.ch
License: MIT
Platform: UNKNOWN
Classifier: Programming Language :: Python :: 3
Requires-Python: >=3.7
License-File: LICENSE
